fpga/de10_nano/rtl/event_capture.sv
module event_capture(
    input wire          clk,
    input wire          rst_n,
    input wire          event_sync,
    input wire [63:0]   count,
    output reg [63:0]   timestamp,
    output reg          timestamp_valid
);

    reg                 event_prev;

    always @(posedge clk or negedge rst_n) begin
        if (!rst_n) begin
            event_prev      <= 1'b0;
            timestamp       <= 64'd0;
            timestamp_valid <= 1'b0;
        end else begin
            event_prev      <= event_sync;
            timestamp_valid <= 1'b0;

            if (event_sync && !event_prev) begin
                timestamp       <= count;
                timestamp_valid <= 1'b1;
        end

        
        end
    end
endmodule

fpga/de10_nano/rtl/timestamp_counter.sv
module timestamp_counter (
    input wire clk,
    input wire rst_n,
    output reg [63:0] count
    );


    always @(posedge clk or negedge rst_n) begin
        if (!rst_n) begin
            count <= 64'd0;
        end else begin
            count <= count + 64'd1;
        end
    end
endmodule

fpga/de10_nano/rtl/cdc_sync.sv
module cdc_sync(
    input  wire         clk,
    input  wire         rst_n,
    input  wire         async_event_in,
    output wire         event_sync
);

    reg event_meta;     // First sync flop
    reg event_sync_d;  // Second sync flop

    always @(posedge clk or negedge rst_n) begin
        if (!rst_n) begin
            event_meta      <= 1'b0;
            event_sync_d    <= 1'b0;
        end else begin
            event_meta      <= async_event_in;
            event_sync_d    <= event_meta;
        end
    end 
    assign event_sync       = event_sync_d;
endmodule

fpga/de10_nano/sim/tb_timestamp.sv
`timescale 1ns/1ps

module tb_timestamp;

    reg clk;
    reg rst_n;
    reg async_event_in;

    wire event_sync;
    wire [63:0] count;
    wire [63:0] timestamp;
    wire timestamp_valid;

    integer valid_count;
    reg [63:0] timestamp_1;
    reg [63:0] timestamp_2;

    // 50 MHz clock = 20 ns period
    initial begin
        clk = 1'b0;
        forever #10 clk = ~clk;
    end

    cdc_sync u_cdc_sync (
        .clk            (clk),
        .rst_n          (rst_n),
        .async_event_in (async_event_in),
        .event_sync     (event_sync)
    );

    timestamp_counter u_timestamp_counter (
        .clk   (clk),
        .rst_n (rst_n),
        .count (count)
    );

    event_capture u_event_capture (
        .clk             (clk),
        .rst_n           (rst_n),
        .event_sync      (event_sync),
        .count           (count),
        .timestamp       (timestamp),
        .timestamp_valid (timestamp_valid)
    );

    // Count every timestamp capture
    always @(posedge timestamp_valid) begin
        valid_count = valid_count + 1;

        if (valid_count == 1)
            timestamp_1 = timestamp;

        if (valid_count == 2)
            timestamp_2 = timestamp;

        $display(
            "CAPTURE %0d: sim_time=%0t ns timestamp=%0d",
            valid_count,
            $time,
            timestamp
        );
    end

    initial begin

        $dumpfile("sim/timestamp.vcd");
        $dumpvars(0, tb_timestamp);

        valid_count   = 0;
        timestamp_1   = 0;
        timestamp_2   = 0;

        rst_n          = 0;
        async_event_in = 0;

        // Hold reset for several clocks
        #100;
        rst_n = 1;

        // Don't align this event perfectly with the FPGA clock.
        // It is supposed to be asynchronous.
        #137;

        // Event #1
        async_event_in = 1;

        // Keep HIGH a long time.
        // This should STILL cause only one timestamp.
        #500;
        async_event_in = 0;

        #300;

        // After first complete event, exactly one capture should exist
        if (valid_count != 1) begin
            $fatal(1,
                "FAIL: expected 1 capture after first event, got %0d",
                valid_count
            );
        end

        // Event #2
        #73;
        async_event_in = 1;
        #400;
        async_event_in = 0;

        #300;

        if (valid_count != 2) begin
            $fatal(1,
                "FAIL: expected 2 total captures, got %0d",
                valid_count
            );
        end

        if (timestamp_2 <= timestamp_1) begin
            $fatal(1,
                "FAIL: second timestamp (%0d) is not later than first (%0d)",
                timestamp_2,
                timestamp_1
            );
        end

        $display("");
        $display("PASS");
        $display("timestamp 1 = %0d", timestamp_1);
        $display("timestamp 2 = %0d", timestamp_2);
        $display("delta       = %0d FPGA clocks",
                 timestamp_2 - timestamp_1);
        $display("delta       = %0d ns",
                 (timestamp_2 - timestamp_1) * 20);

        $finish;
    end

endmodule

fpga/de10_nano/sim/timestamp.vcd
$date
	Tue Sep 29 19:02:57 2026
$end
$version
	Icarus Verilog
$end
$timescale
	1ps
$end
$scope module tb_timestamp $end
$var wire 1 ! timestamp_valid $end
$var wire 64 " timestamp [63:0] $end
$var wire 1 # event_sync $end
$var wire 64 $ count [63:0] $end
$var reg 1 % async_event_in $end
$var reg 1 & clk $end
$var reg 1 ' rst_n $end
$var reg 64 ( timestamp_1 [63:0] $end
$var reg 64 ) timestamp_2 [63:0] $end
$var integer 32 * valid_count [31:0] $end
$scope module u_cdc_sync $end
$var wire 1 % async_event_in $end
$var wire 1 & clk $end
$var wire 1 # event_sync $end
$var wire 1 ' rst_n $end
$var reg 1 + event_meta $end
$var reg 1 , event_sync_d $end
$upscope $end
$scope module u_event_capture $end
$var wire 1 & clk $end
$var wire 1 # event_sync $end
$var wire 1 ' rst_n $end
$var wire 64 - count [63:0] $end
$var reg 1 . event_prev $end
$var reg 64 / timestamp [63:0] $end
$var reg 1 ! timestamp_valid $end
$upscope $end
$scope module u_timestamp_counter $end
$var wire 1 & clk $end
$var wire 1 ' rst_n $end
$var reg 64 0 count [63:0] $end
$upscope $end
$upscope $end
$enddefinitions $end
$comment Show the parameter values. $end
$dumpall
$end
#0
$dumpvars
b0 0
b0 /
0.
b0 -
0,
0+
b0 *
b0 )
b0 (
0'
0&
0%
b0 $
0#
b0 "
0!
$end
#10000
1&
#20000
0&
#30000
1&
#40000
0&
#50000
1&
#60000
0&
#70000
1&
#80000
0&
#90000
1&
#100000
0&
1'
#110000
b1 $
b1 -
b1 0
1&
#120000
0&
#130000
b10 $
b10 -
b10 0
1&
#140000
0&
#150000
b11 $
b11 -
b11 0
1&
#160000
0&
#170000
b100 $
b100 -
b100 0
1&
#180000
0&
#190000
b101 $
b101 -
b101 0
1&
#200000
0&
#210000
b110 $
b110 -
b110 0
1&
#220000
0&
#230000
b111 $
b111 -
b111 0
1&
#237000
1%
#240000
0&
#250000
b1000 $
b1000 -
b1000 0
1+
1&
#260000
0&
#270000
1#
1,
b1001 $
b1001 -
b1001 0
1&
#280000
0&
#290000
b1001 (
b1 *
1!
b1001 "
b1001 /
1.
b1010 $
b1010 -
b1010 0
1&
#300000
0&
#310000
b1011 $
b1011 -
b1011 0
0!
1&
#320000
0&
#330000
b1100 $
b1100 -
b1100 0
1&
#340000
0&
#350000
b1101 $
b1101 -
b1101 0
1&
#360000
0&
#370000
b1110 $
b1110 -
b1110 0
1&
#380000
0&
#390000
b1111 $
b1111 -
b1111 0
1&
#400000
0&
#410000
b10000 $
b10000 -
b10000 0
1&
#420000
0&
#430000
b10001 $
b10001 -
b10001 0
1&
#440000
0&
#450000
b10010 $
b10010 -
b10010 0
1&
#460000
0&
#470000
b10011 $
b10011 -
b10011 0
1&
#480000
0&
#490000
b10100 $
b10100 -
b10100 0
1&
#500000
0&
#510000
b10101 $
b10101 -
b10101 0
1&
#520000
0&
#530000
b10110 $
b10110 -
b10110 0
1&
#540000
0&
#550000
b10111 $
b10111 -
b10111 0
1&
#560000
0&
#570000
b11000 $
b11000 -
b11000 0
1&
#580000
0&
#590000
b11001 $
b11001 -
b11001 0
1&
#600000
0&
#610000
b11010 $
b11010 -
b11010 0
1&
#620000
0&
#630000
b11011 $
b11011 -
b11011 0
1&
#640000
0&
#650000
b11100 $
b11100 -
b11100 0
1&
#660000
0&
#670000
b11101 $
b11101 -
b11101 0
1&
#680000
0&
#690000
b11110 $
b11110 -
b11110 0
1&
#700000
0&
#710000
b11111 $
b11111 -
b11111 0
1&
#720000
0&
#730000
b100000 $
b100000 -
b100000 0
1&
#737000
0%
#740000
0&
#750000
0+
b100001 $
b100001 -
b100001 0
1&
#760000
0&
#770000
b100010 $
b100010 -
b100010 0
0#
0,
1&
#780000
0&
#790000
b100011 $
b100011 -
b100011 0
0.
1&
#800000
0&
#810000
b100100 $
b100100 -
b100100 0
1&
#820000
0&
#830000
b100101 $
b100101 -
b100101 0
1&
#840000
0&
#850000
b100110 $
b100110 -
b100110 0
1&
#860000
0&
#870000
b100111 $
b100111 -
b100111 0
1&
#880000
0&
#890000
b101000 $
b101000 -
b101000 0
1&
#900000
0&
#910000
b101001 $
b101001 -
b101001 0
1&
#920000
0&
#930000
b101010 $
b101010 -
b101010 0
1&
#940000
0&
#950000
b101011 $
b101011 -
b101011 0
1&
#960000
0&
#970000
b101100 $
b101100 -
b101100 0
1&
#980000
0&
#990000
b101101 $
b101101 -
b101101 0
1&
#1000000
0&
#1010000
b101110 $
b101110 -
b101110 0
1&
#1020000
0&
#1030000
b101111 $
b101111 -
b101111 0
1&
#1040000
0&
#1050000
b110000 $
b110000 -
b110000 0
1&
#1060000
0&
#1070000
b110001 $
b110001 -
b110001 0
1&
#1080000
0&
#1090000
b110010 $
b110010 -
b110010 0
1&
#1100000
0&
#1110000
1+
b110011 $
b110011 -
b110011 0
1&
1%
#1120000
0&
#1130000
b110100 $
b110100 -
b110100 0
1#
1,
1&
#1140000
0&
#1150000
b110100 )
b10 *
b110101 $
b110101 -
b110101 0
1!
b110100 "
b110100 /
1.
1&
#1160000
0&
#1170000
0!
b110110 $
b110110 -
b110110 0
1&
#1180000
0&
#1190000
b110111 $
b110111 -
b110111 0
1&
#1200000
0&
#1210000
b111000 $
b111000 -
b111000 0
1&
#1220000
0&
#1230000
b111001 $
b111001 -
b111001 0
1&
#1240000
0&
#1250000
b111010 $
b111010 -
b111010 0
1&
#1260000
0&
#1270000
b111011 $
b111011 -
b111011 0
1&
#1280000
0&
#1290000
b111100 $
b111100 -
b111100 0
1&
#1300000
0&
#1310000
b111101 $
b111101 -
b111101 0
1&
#1320000
0&
#1330000
b111110 $
b111110 -
b111110 0
1&
#1340000
0&
#1350000
b111111 $
b111111 -
b111111 0
1&
#1360000
0&
#1370000
b1000000 $
b1000000 -
b1000000 0
1&
#1380000
0&
#1390000
b1000001 $
b1000001 -
b1000001 0
1&
#1400000
0&
#1410000
b1000010 $
b1000010 -
b1000010 0
1&
#1420000
0&
#1430000
b1000011 $
b1000011 -
b1000011 0
1&
#1440000
0&
#1450000
b1000100 $
b1000100 -
b1000100 0
1&
#1460000
0&
#1470000
b1000101 $
b1000101 -
b1000101 0
1&
#1480000
0&
#1490000
b1000110 $
b1000110 -
b1000110 0
1&
#1500000
0&
#1510000
0+
b1000111 $
b1000111 -
b1000111 0
1&
0%
#1520000
0&
#1530000
b1001000 $
b1001000 -
b1001000 0
0#
0,
1&
#1540000
0&
#1550000
b1001001 $
b1001001 -
b1001001 0
0.
1&
#1560000
0&
#1570000
b1001010 $
b1001010 -
b1001010 0
1&
#1580000
0&
#1590000
b1001011 $
b1001011 -
b1001011 0
1&
#1600000
0&
#1610000
b1001100 $
b1001100 -
b1001100 0
1&
#1620000
0&
#1630000
b1001101 $
b1001101 -
b1001101 0
1&
#1640000
0&
#1650000
b1001110 $
b1001110 -
b1001110 0
1&
#1660000
0&
#1670000
b1001111 $
b1001111 -
b1001111 0
1&
#1680000
0&
#1690000
b1010000 $
b1010000 -
b1010000 0
1&
#1700000
0&
#1710000
b1010001 $
b1010001 -
b1010001 0
1&
#1720000
0&
#1730000
b1010010 $
b1010010 -
b1010010 0
1&
#1740000
0&
#1750000
b1010011 $
b1010011 -
b1010011 0
1&
#1760000
0&
#1770000
b1010100 $
b1010100 -
b1010100 0
1&
#1780000
0&
#1790000
b1010101 $
b1010101 -
b1010101 0
1&
#1800000
0&
#1810000
b1010110 $
b1010110 -
b1010110 0
1&
